[
  {
    "scientific_name": "Caiman yacare",
    "common_names": [
      {
        "lang": "de",
        "name": "Yacare-Kaiman",
        "synonyms": [
          "Südlicher Brillenkaiman"
        ]
      },
      {
        "lang": "en",
        "name": "Yacare Caiman"
      },
      {
        "lang": "es",
        "name": "Yacaré"
      },
      {
        "lang": "fi",
        "name": "Jacarenkaimaani"
      },
      {
        "lang": "hu",
        "name": "Yacare kajmán"
      },
      {
        "lang": "pl",
        "name": "Kajman żakare"
      },
      {
        "lang": "pt",
        "name": "Jacaré",
        "synonyms": [
          "Jacaré-do-Paraguai",
          "Jacaré-do-pantanal"
        ]
      }
    ]
  },
  {
    "scientific_name": "Caiman latirostris",
    "common_names": [
      {
        "lang": "bg",
        "name": "Широкомуцунест кайман"
      },
      {
        "lang": "de",
        "name": "Breitschnauzenkaiman"
      },
      {
        "lang": "en",
        "name": "Broad-snouted caiman",
        "synonyms": [
          "Black Caiman"
        ]
      },
      {
        "lang": "es",
        "name": "Yacaré overo"
      },
      {
        "lang": "fi",
        "name": "Leveäkuonokaimaani"
      },
      {
        "lang": "fr",
        "name": "Caïman à museau large"
      },
      {
        "lang": "he",
        "name": "קיימן רחב חרטום"
      },
      {
        "lang": "hu",
        "name": "Sakáre-kajmán"
      },
      {
        "lang": "ja",
        "name": "クチヒロカイマン"
      },
      {
        "lang": "nl",
        "name": "Breedsnuitkaaiman"
      },
      {
        "lang": "pl",
        "name": "Kajman szerokopyski"
      },
      {
        "lang": "pt",
        "name": "Jacaré-de-papo-amarelo"
      },
      {
        "lang": "tr",
        "name": "Geniş burunlu kayman"
      }
    ]
  },
  {
    "scientific_name": "Caiman crocodilus",
    "common_names": [
      {
        "lang": "ar",
        "name": "الكيمن ذو النظّارة"
      },
      {
        "lang": "bg",
        "name": "Очилат кайман"
      },
      {
        "lang": "br",
        "name": "Kaiman lunedek"
      },
      {
        "lang": "ca",
        "name": "Caiman d'ulleres"
      },
      {
        "lang": "cs",
        "name": "Kajman brýlový"
      },
      {
        "lang": "de",
        "name": "Krokodilkaiman",
        "synonyms": [
          "(Nördlicher) Brillenkaiman"
        ]
      },
      {
        "lang": "es",
        "name": "Caimán de anteojos"
      },
      {
        "lang": "fi",
        "name": "Silmälasikaimaani"
      },
      {
        "lang": "fr",
        "name": "Caïman à lunettes"
      },
      {
        "lang": "hr",
        "name": "Kajman naočar"
      },
      {
        "lang": "he",
        "name": "קיימן ממושקף"
      },
      {
        "lang": "hu",
        "name": "Pápaszemes kajmán"
      },
      {
        "lang": "it",
        "name": "Caimano dagli occhiali",
        "synonyms": [
          "caimano comune"
        ]
      },
      {
        "lang": "ja",
        "name": "メガネカイマン"
      },
      {
        "lang": "mk",
        "name": "Очилен кајман"
      },
      {
        "lang": "nl",
        "name": "Brilkaaiman"
      },
      {
        "lang": "no",
        "name": "Brillekaiman"
      },
      {
        "lang": "pnb",
        "name": "کائمان مگرمچھ"
      },
      {
        "lang": "pl",
        "name": "Kajman krokodylowy",
        "synonyms": [
          "kajman okularowy"
        ]
      },
      {
        "lang": "pt",
        "name": "Jacaretinga",
        "synonyms": [
          "Jacaré-de-óculos"
        ]
      },
      {
        "lang": "qu",
        "name": "Yuraq lagartu"
      },
      {
        "lang": "ru",
        "name": "Крокодиловый кайман"
      },
      {
        "lang": "simple",
        "name": "Spectacled Caiman"
      },
      {
        "lang": "sk",
        "name": "Kajman okuliarnatý"
      },
      {
        "lang": "sr",
        "name": "Обични кајман",
        "synonyms": [
          "Крокодил-кајман"
        ]
      },
      {
        "lang": "sv",
        "name": "Glasögonkajman"
      },
      {
        "lang": "tr",
        "name": "Gözlüklü kayman"
      },
      {
        "lang": "uk",
        "name": "Крокодиловий кайман"
      },
      {
        "lang": "zh-yue",
        "name": "眼鏡凱門鱷"
      },
      {
        "lang": "zh",
        "name": "眼鏡凱門鱷"
      }
    ]
  }
]
