[
  {
    "scientific_name": "Liomys spectabilis",
    "common_names": [
      {
        "lang": "en",
        "name": "Jaliscan Spiny Pocket Mouse"
      }
    ]
  },
  {
    "scientific_name": "Liomys salvini",
    "common_names": [
      {
        "lang": "en",
        "name": "Salvin's Spiny Pocket Mouse"
      }
    ]
  },
  {
    "scientific_name": "Liomys pictus",
    "common_names": [
      {
        "lang": "en",
        "name": "Painted Spiny Pocket Mouse"
      }
    ]
  },
  {
    "scientific_name": "Liomys irroratus",
    "common_names": [
      {
        "lang": "en",
        "name": "Mexican Spiny Pocket Mouse"
      }
    ]
  },
  {
    "scientific_name": "Liomys adspersus",
    "common_names": [
      {
        "lang": "en",
        "name": "Panamanian Spiny Pocket Mouse"
      }
    ]
  }
]
