[
  {
    "scientific_name": "Taurotragus oryx",
    "common_names": [
      {
        "lang": "Afr",
        "name": "Eland"
      },
      {
        "lang": "cs",
        "name": "Antilopa losí"
      },
      {
        "lang": "de",
        "name": "Elenantilope"
      },
      {
        "lang": "en",
        "name": "Common Eland"
      },
      {
        "lang": "eo",
        "name": "Elando"
      },
      {
        "lang": "es",
        "name": "Eland del Cabo"
      },
      {
        "lang": "fr",
        "name": "Éland"
      },
      {
        "lang": "hu",
        "name": "Jávorantilop"
      },
      {
        "lang": "it",
        "name": "L'antilope alcina",
        "synonyms": [
          "eland comune"
        ]
      },
      {
        "lang": "ja",
        "name": "エランド"
      },
      {
        "lang": "lt",
        "name": "Kana"
      },
      {
        "lang": "nl",
        "name": "Elandantilope"
      },
      {
        "lang": "pl",
        "name": "Eland"
      },
      {
        "lang": "pt",
        "name": "Eland"
      },
      {
        "lang": "sl",
        "name": "Eland antilopa"
      },
      {
        "lang": "sv",
        "name": "Elandantilop"
      },
      {
        "lang": "tr",
        "name": "Bayağı boğa antilobu"
      },
      {
        "lang": "uk",
        "name": "Антилопа канна"
      },
      {
        "lang": "th",
        "name": "อีแลนด์",
        "synonyms": [
          "อีแลนด์ธรรมดา"
        ]
      }
    ]
  },
  {
    "scientific_name": "Taurotragus derbianus",
    "common_names": [
      {
        "lang": "cs",
        "name": "Antilopa Derbyho"
      },
      {
        "lang": "en",
        "name": "Giant eland",
        "synonyms": [
          "Derby Eland"
        ]
      },
      {
        "lang": "es",
        "name": "Eland gigante"
      },
      {
        "lang": "fi",
        "name": "Jättiläishirviantilooppi"
      },
      {
        "lang": "fr",
        "name": "Élan de derby",
        "synonyms": [
          "Éland de derby"
        ]
      },
      {
        "lang": "hu",
        "name": "Óriás jávorantilop"
      },
      {
        "lang": "ja",
        "name": "ジャイアントイランド"
      },
      {
        "lang": "nl",
        "name": "Reuzenelandantilope"
      },
      {
        "lang": "pl",
        "name": "Oreas"
      },
      {
        "lang": "sv",
        "name": "Jätteeland"
      },
      {
        "lang": "tr",
        "name": "Dev boğa antilobu"
      }
    ]
  }
]
