[
  {
    "scientific_name": "Aegypius monachus",
    "common_names": [
      {
        "lang": "ak",
        "name": "pete"
      },
      {
        "lang": "az",
        "name": "Qara kərkəs"
      },
      {
        "lang": "be",
        "name": "Чорны грыф"
      },
      {
        "lang": "be-x-old",
        "name": "Чорны грыф"
      },
      {
        "lang": "bg",
        "name": "Черен лешояд"
      },
      {
        "lang": "br",
        "name": "Gup du"
      },
      {
        "lang": "ca",
        "name": "Voltor negre"
      },
      {
        "lang": "cs",
        "name": "Sup hnědý"
      },
      {
        "lang": "da",
        "name": "Munkegrib"
      },
      {
        "lang": "de",
        "name": "Mönchsgeier"
      },
      {
        "lang": "el",
        "name": "Μαυρόγυπας"
      },
      {
        "lang": "en",
        "name": "Cinereous Vulture"
      },
      {
        "lang": "eo",
        "name": "Nigra grifo"
      },
      {
        "lang": "es",
        "name": "Buitre negro"
      },
      {
        "lang": "fi",
        "name": "Munkkikorppikotka"
      },
      {
        "lang": "fr",
        "name": "Vautour Moine"
      },
      {
        "lang": "gl",
        "name": "Voitre negro"
      },
      {
        "lang": "he",
        "name": "עזנייה שחורה"
      },
      {
        "lang": "hu",
        "name": "Barátkeselyű"
      },
      {
        "lang": "hy",
        "name": "Անգղ սև"
      },
      {
        "lang": "id",
        "name": "Hering Hitam Eurasia"
      },
      {
        "lang": "it",
        "name": "Avvoltoio monaco"
      },
      {
        "lang": "ja",
        "name": "クロハゲワシ"
      },
      {
        "lang": "ka",
        "name": "სვავი"
      },
      {
        "lang": "ko",
        "name": "독수리"
      },
      {
        "lang": "lv",
        "name": "Melnais grifs"
      },
      {
        "lang": "ms",
        "name": "Hering Hitam"
      },
      {
        "lang": "nl",
        "name": "Monniksgier"
      },
      {
        "lang": "no",
        "name": "Munkegribb"
      },
      {
        "lang": "oc",
        "name": "Vutre monge"
      },
      {
        "lang": "pl",
        "name": "Sęp kasztanowaty"
      },
      {
        "lang": "pt",
        "name": "Abutre-monge"
      },
      {
        "lang": "ru",
        "name": "Чёрный гриф"
      },
      {
        "lang": "sq",
        "name": "Shqiponjë e zezë"
      },
      {
        "lang": "sl",
        "name": "Rjavi jastreb"
      },
      {
        "lang": "sv",
        "name": "Grågam"
      },
      {
        "lang": "th",
        "name": "แร้งดำหิมาลัย"
      },
      {
        "lang": "tk",
        "name": "Gajar"
      },
      {
        "lang": "tr",
        "name": "Kara akbaba"
      },
      {
        "lang": "uk",
        "name": "Гриф чорний"
      },
      {
        "lang": "vi",
        "name": "Đại bàng đầu trọc"
      },
      {
        "lang": "zh",
        "name": "秃鹫"
      },
      {
        "lang": "zh-hant",
        "name": "禿鷲"
      }
    ]
  },
  {
    "scientific_name": "Aegypius jinniushanensis",
    "common_names": []
  }
]
