[
  {
    "scientific_name": "Aepypodius bruijnii",
    "common_names": [
      {
        "lang": "en",
        "name": "Waigeo brushturkey",
        "synonyms": [
          "Bruijn's Brush-turkey"
        ]
      }
    ]
  },
  {
    "scientific_name": "Aepypodius arfakianus",
    "common_names": [
      {
        "lang": "en",
        "name": "Wattled Brush-turkey"
      },
      {
        "lang": "es",
        "name": "Talégalo carunculado"
      },
      {
        "lang": "fi",
        "name": "Helttatalekana"
      },
      {
        "lang": "fr",
        "name": "Talégalle des Arfak"
      },
      {
        "lang": "nl",
        "name": "Kamboskalkoen"
      },
      {
        "lang": "sv",
        "name": "Kambuskhöna"
      }
    ]
  }
]
