[
  {
    "scientific_name": "Erythrotriorchis radiatus",
    "common_names": [
      {
        "lang": "en",
        "name": "Red Goshawk"
      },
      {
        "lang": "es",
        "name": "Azor rojo"
      },
      {
        "lang": "fr",
        "name": "Autour rouge"
      },
      {
        "lang": "hu",
        "name": "Rókahéja"
      },
      {
        "lang": "pl",
        "name": "Jastrząb kreskowany"
      }
    ]
  },
  {
    "scientific_name": "Erythrotriorchis buergersi",
    "common_names": [
      {
        "lang": "cs",
        "name": "Jestřáb kaštanovohřbetý"
      },
      {
        "lang": "en",
        "name": "Chestnut-shouldered Goshawk"
      },
      {
        "lang": "es",
        "name": "Azor de Burgers"
      },
      {
        "lang": "hu",
        "name": "Kucsmás rókahéja"
      },
      {
        "lang": "pl",
        "name": "Jastrząb kasztanowaty"
      }
    ]
  }
]
