[
  {
    "scientific_name": "Scytalopus zimmeri",
    "common_names": [
      {
        "lang": "fi",
        "name": "Kivikkotapakulo"
      },
      {
        "lang": "en",
        "name": "Zimmer's tapaculo"
      },
      {
        "lang": "es",
        "name": "Churrín de Zimmer"
      }
    ]
  },
  {
    "scientific_name": "Scytalopus vicinior",
    "common_names": [
      {
        "lang": "fi",
        "name": "Nuohoojatapakulo"
      },
      {
        "lang": "es",
        "name": "Churrín de Nariño"
      },
      {
        "lang": "en",
        "name": "Nariño tapaculo"
      }
    ]
  },
  {
    "scientific_name": "Scytalopus urubambae",
    "common_names": [
      {
        "lang": "fi",
        "name": "Vilcabambantapakulo"
      },
      {
        "lang": "en",
        "name": "Vilcabamba tapaculo"
      },
      {
        "lang": "es",
        "name": "Churrín de Vilcabamba"
      }
    ]
  },
  {
    "scientific_name": "Scytalopus unicolor",
    "common_names": [
      {
        "lang": "en",
        "name": "Unicolored tapaculo"
      },
      {
        "lang": "es",
        "name": "Churrín unicolor"
      }
    ]
  },
  {
    "scientific_name": "Scytalopus superciliaris",
    "common_names": [
      {
        "lang": "fi",
        "name": "Valkokulmatapakulo"
      },
      {
        "lang": "es",
        "name": "Churrín cejiblanco"
      },
      {
        "lang": "en",
        "name": "White-browed tapaculo"
      }
    ]
  },
  {
    "scientific_name": "Scytalopus stilesi",
    "common_names": [
      {
        "lang": "en",
        "name": "Stile's Tapaculo"
      },
      {
        "lang": "es",
        "name": "Tapaculo de Stiles"
      }
    ]
  },
  {
    "scientific_name": "Scytalopus spillmanni",
    "common_names": [
      {
        "lang": "en",
        "name": "Spillmann's Tapaculo"
      },
      {
        "lang": "fi",
        "name": "Ecuadorintapakulo"
      },
      {
        "lang": "es",
        "name": "Churrín de Spillmann"
      }
    ]
  },
  {
    "scientific_name": "Scytalopus speluncae",
    "common_names": [
      {
        "lang": "en",
        "name": "Mouse-colored tapaculo"
      },
      {
        "lang": "es",
        "name": "Churrín plomizo"
      },
      {
        "lang": "pt",
        "name": "Tapaculo-preto"
      }
    ]
  },
  {
    "scientific_name": "Scytalopus simonsi",
    "common_names": [
      {
        "lang": "fi",
        "name": "Punantapakulo"
      },
      {
        "lang": "en",
        "name": "Puna tapaculo"
      },
      {
        "lang": "es",
        "name": "Churrín de la Puna"
      }
    ]
  },
  {
    "scientific_name": "Scytalopus schulenbergi",
    "common_names": [
      {
        "lang": "en",
        "name": "Diademed Tapaculo"
      },
      {
        "lang": "fi",
        "name": "Valko-otsatapakulo"
      },
      {
        "lang": "pl",
        "name": "krytonosek diademowy"
      },
      {
        "lang": "es",
        "name": "Churrín diademado"
      }
    ]
  },
  {
    "scientific_name": "Scytalopus sanctaemartae",
    "common_names": [
      {
        "lang": "fi",
        "name": "Santamartantapakulo"
      },
      {
        "lang": "es",
        "name": "Churrín de Santa Marta"
      },
      {
        "lang": "en",
        "name": "Santa Marta tapaculo"
      }
    ]
  },
  {
    "scientific_name": "Scytalopus rodriguezi",
    "common_names": [
      {
        "lang": "en",
        "name": "Upper Magdalena tapaculo"
      },
      {
        "lang": "es",
        "name": "Tapaculo del Alto Magdalena"
      }
    ]
  },
  {
    "scientific_name": "Scytalopus robbinsi",
    "common_names": [
      {
        "lang": "en",
        "name": "Ecuadorian Tapaculo"
      },
      {
        "lang": "fr",
        "name": "Mérulaxe de Robbins"
      },
      {
        "lang": "de",
        "name": "Robbinstapaculomm"
      },
      {
        "lang": "es",
        "name": "Churrín de El Oro"
      }
    ]
  },
  {
    "scientific_name": "Scytalopus petrophilus",
    "common_names": [
      {
        "lang": "en",
        "name": "Rock Tapaculo"
      },
      {
        "lang": "es",
        "name": "Churrín roquero"
      },
      {
        "lang": "pt",
        "name": "Tapaculo-serrano"
      }
    ]
  },
  {
    "scientific_name": "Scytalopus perijanus",
    "common_names": [
      {
        "lang": "en",
        "name": "Perijá tapaculo"
      },
      {
        "lang": "es",
        "name": "Tapaculo de Perijá"
      }
    ]
  },
  {
    "scientific_name": "Scytalopus parvirostris",
    "common_names": [
      {
        "lang": "en",
        "name": "Trilling Tapaculo"
      },
      {
        "lang": "es",
        "name": "Churrín trinador; tapaculo trinador"
      }
    ]
  },
  {
    "scientific_name": "Scytalopus parkeri",
    "common_names": [
      {
        "lang": "en",
        "name": "Chusquea tapaculo"
      },
      {
        "lang": "es",
        "name": "Churrín de Chusquea; tapaculo de Chusquea"
      }
    ]
  },
  {
    "scientific_name": "Scytalopus panamensis",
    "common_names": [
      {
        "lang": "fi",
        "name": "Harmaakurkkutapakulo"
      },
      {
        "lang": "en",
        "name": "Tacarcuna tapaculo"
      },
      {
        "lang": "es",
        "name": "Churrín panameño"
      }
    ]
  },
  {
    "scientific_name": "Scytalopus pachecoi",
    "common_names": [
      {
        "lang": "en",
        "name": "Planalto tapaculo"
      },
      {
        "lang": "es",
        "name": "Tapaculo del Planalto",
        "synonyms": [
          "churrín de Pacheco"
        ]
      },
      {
        "lang": "pt",
        "name": "Tapaculo-ferreirinho"
      }
    ]
  },
  {
    "scientific_name": "Scytalopus opacus",
    "common_names": [
      {
        "lang": "en",
        "name": "Paramo tapaculo"
      },
      {
        "lang": "es",
        "name": "Tapaculo opaco"
      }
    ]
  },
  {
    "scientific_name": "Scytalopus novacapitalis",
    "common_names": [
      {
        "lang": "en",
        "name": "Brasília Tapaculo"
      },
      {
        "lang": "es",
        "name": "Churrín de Brasilia"
      },
      {
        "lang": "fi",
        "name": "Brasiliantapakulo"
      },
      {
        "lang": "pt",
        "name": "Tapaculo de Brasilia"
      }
    ]
  },
  {
    "scientific_name": "Scytalopus micropterus",
    "common_names": [
      {
        "lang": "fi",
        "name": "Kolumbiantapakulo"
      },
      {
        "lang": "es",
        "name": "Churrín colilargo"
      },
      {
        "lang": "en",
        "name": "Long-tailed tapaculo"
      }
    ]
  },
  {
    "scientific_name": "Scytalopus meridanus",
    "common_names": [
      {
        "lang": "fi",
        "name": "Méridantapakulo"
      },
      {
        "lang": "en",
        "name": "Mérida tapaculo"
      },
      {
        "lang": "es",
        "name": "Churrín de Mérida"
      }
    ]
  },
  {
    "scientific_name": "Scytalopus magellanicus",
    "common_names": [
      {
        "lang": "fi",
        "name": "Andientapakulo"
      },
      {
        "lang": "es",
        "name": "Churrín magallánico"
      },
      {
        "lang": "en",
        "name": "Magellanic tapaculo"
      }
    ]
  },
  {
    "scientific_name": "Scytalopus macropus",
    "common_names": [
      {
        "lang": "fi",
        "name": "Koskitapakulo"
      },
      {
        "lang": "es",
        "name": "Churrín patudo"
      },
      {
        "lang": "en",
        "name": "Large-footed tapaculo"
      }
    ]
  },
  {
    "scientific_name": "Scytalopus latrans",
    "common_names": [
      {
        "lang": "es",
        "name": "Churrín negruzco"
      },
      {
        "lang": "en",
        "name": "Blackish tapaculo"
      }
    ]
  },
  {
    "scientific_name": "Scytalopus latebricola",
    "common_names": [
      {
        "lang": "fi",
        "name": "Peukaloistapakulo"
      },
      {
        "lang": "en",
        "name": "Brown-rumped tapaculo"
      },
      {
        "lang": "es",
        "name": "Churrín ratona"
      }
    ]
  },
  {
    "scientific_name": "Scytalopus iraiensis",
    "common_names": [
      {
        "lang": "en",
        "name": "Marsh Tapaculo"
      },
      {
        "lang": "pt",
        "name": "Macuquinho-do-brejo"
      },
      {
        "lang": "fi",
        "name": "Luhtatapakulo"
      }
    ]
  },
  {
    "scientific_name": "Scytalopus griseicollis",
    "common_names": [
      {
        "lang": "fi",
        "name": "Kolumbianandientapakulo"
      },
      {
        "lang": "es",
        "name": "Churrín de matorral"
      },
      {
        "lang": "en",
        "name": "Pale-bellied tapaculo"
      }
    ]
  },
  {
    "scientific_name": "Scytalopus gonzagai",
    "common_names": [
      {
        "lang": "en",
        "name": "Boa Nova tapaculo"
      },
      {
        "lang": "es",
        "name": "Churrín de Bahía"
      },
      {
        "lang": "pt",
        "name": "Tapaculo-preto-baiano"
      }
    ]
  },
  {
    "scientific_name": "Scytalopus gettyae",
    "common_names": [
      {
        "lang": "en",
        "name": "Junin tapaculo"
      },
      {
        "lang": "es",
        "name": "Tapaculo de Junín"
      }
    ]
  },
  {
    "scientific_name": "Scytalopus fuscus",
    "common_names": [
      {
        "lang": "fi",
        "name": "Chilentapakulo"
      },
      {
        "lang": "en",
        "name": "Dusky tapaculo"
      },
      {
        "lang": "es",
        "name": "Churrín sombrío"
      }
    ]
  },
  {
    "scientific_name": "Scytalopus femoralis",
    "common_names": [
      {
        "lang": "en",
        "name": "Rufous-vented Tapaculo"
      },
      {
        "lang": "fi",
        "name": "Ruskoperätapakulo"
      },
      {
        "lang": "es",
        "name": "Churrín ventrirrufo"
      }
    ]
  },
  {
    "scientific_name": "Scytalopus diamantinensis",
    "common_names": [
      {
        "lang": "en",
        "name": "Diamantina tapaculo"
      },
      {
        "lang": "es",
        "name": "Churrín de Diamantina"
      },
      {
        "lang": "pt",
        "name": "Tapaculo-da-chapada-diamantina"
      }
    ]
  },
  {
    "scientific_name": "Scytalopus chocoensis",
    "common_names": [
      {
        "lang": "en",
        "name": "Chocó tapaculo"
      },
      {
        "lang": "es",
        "name": "Churrín del Chocó"
      }
    ]
  },
  {
    "scientific_name": "Scytalopus caracae",
    "common_names": [
      {
        "lang": "fi",
        "name": "Venezuelantapakulo"
      },
      {
        "lang": "en",
        "name": "Caracas tapaculo"
      },
      {
        "lang": "es",
        "name": "Churrín de Caracas"
      }
    ]
  },
  {
    "scientific_name": "Scytalopus canus",
    "common_names": [
      {
        "lang": "fi",
        "name": "Liusketapakulo"
      },
      {
        "lang": "en",
        "name": "Paramillo tapaculo"
      },
      {
        "lang": "es",
        "name": "Churrín paramero"
      }
    ]
  },
  {
    "scientific_name": "Scytalopus bolivianus",
    "common_names": [
      {
        "lang": "en",
        "name": "Southern White-crowned Tapaculo"
      },
      {
        "lang": "fi",
        "name": "Sirittäjätapakulo"
      },
      {
        "lang": "es",
        "name": "Churrín boliviano"
      }
    ]
  },
  {
    "scientific_name": "Scytalopus atratus",
    "common_names": [
      {
        "lang": "fi",
        "name": "Kruunutapakulo"
      },
      {
        "lang": "en",
        "name": "Northern white-crowned tapaculo"
      },
      {
        "lang": "es",
        "name": "Churrín coroniblanco"
      }
    ]
  },
  {
    "scientific_name": "Scytalopus argentifrons",
    "common_names": [
      {
        "lang": "fi",
        "name": "Hopeaotsatapakulo"
      },
      {
        "lang": "en",
        "name": "Silvery-fronted tapaculo"
      },
      {
        "lang": "es",
        "name": "Churrín plateado"
      }
    ]
  },
  {
    "scientific_name": "Scytalopus altirostris",
    "common_names": [
      {
        "lang": "fi",
        "name": "Peruntapakulo"
      },
      {
        "lang": "en",
        "name": "Neblina tapaculo"
      },
      {
        "lang": "es",
        "name": "Churín de Neblina"
      }
    ]
  },
  {
    "scientific_name": "Scytalopus affinis",
    "common_names": [
      {
        "lang": "fi",
        "name": "Vaaleatapakulo"
      },
      {
        "lang": "es",
        "name": "Churrín de Ancash"
      },
      {
        "lang": "en",
        "name": "Ancash tapaculo"
      }
    ]
  },
  {
    "scientific_name": "Scytalopus acutirostris",
    "common_names": [
      {
        "lang": "en",
        "name": "Tschudi's Tapaculo"
      },
      {
        "lang": "fi",
        "name": "Varjotapakulo"
      },
      {
        "lang": "es",
        "name": "Churrín de Tschudi"
      }
    ]
  }
]
